{
	"info": {
		"_postman_id": "b0e3cd17-06b0-4efb-9aa7-3d7a61912cf5",
		"name": "Webhooks",
		"schema": "https://schema.getpostman.com/json/collection/v2.1.0/collection.json"
	},
	"item": [
		{
			"name": "Integration Events ",
			"item": [
				{
					"name": "Get Integration Event by ID",
					"request": {
						"auth": {
							"type": "bearer",
							"bearer": [
								{
									"key": "token",
									"value": "{{token}}",
									"type": "string"
								}
							]
						},
						"method": "GET",
						"header": [],
						"url": {
							"raw": "{{ServerURL}}/organizations/ef8a6670-f522-4fcd-a55e-90aa92d1deb7/IntegrationEvents/241fd289-76ae-499b-b9ee-d2f3d9b3db69",
							"host": [
								"{{ServerURL}}"
							],
							"path": [
								"organizations",
								"ef8a6670-f522-4fcd-a55e-90aa92d1deb7",
								"IntegrationEvents",
								"241fd289-76ae-499b-b9ee-d2f3d9b3db69"
							]
						},
						"description": "Provides an IntegrationEvent's details for a particular IntegrationEvent id"
					},
					"response": []
				},
				{
					"name": "Get All IntegrationEvents",
					"request": {
						"auth": {
							"type": "bearer",
							"bearer": [
								{
									"key": "token",
									"value": "{{token}}",
									"type": "string"
								}
							]
						},
						"method": "GET",
						"header": [],
						"url": {
							"raw": "{{ServerURL}}/organizations/ef8a6670-f522-4fcd-a55e-90aa92d1deb7/IntegrationEvents",
							"host": [
								"{{ServerURL}}"
							],
							"path": [
								"organizations",
								"ef8a6670-f522-4fcd-a55e-90aa92d1deb7",
								"IntegrationEvents"
							]
						},
						"description": "Gets a list of all integration events "
					},
					"response": []
				},
				{
					"name": "Integration Events Lookpu",
					"request": {
						"auth": {
							"type": "bearer",
							"bearer": [
								{
									"key": "token",
									"value": "{{token}}",
									"type": "string"
								}
							]
						},
						"method": "GET",
						"header": [],
						"url": {
							"raw": "{{ServerURL}}/Organizations/8b17fd7e-88f9-4530-beff-a183a44956fa/IntegrationEvents/IntegrationEventLookup\n",
							"host": [
								"{{ServerURL}}"
							],
							"path": [
								"Organizations",
								"8b17fd7e-88f9-4530-beff-a183a44956fa",
								"IntegrationEvents",
								"IntegrationEventLookup\n"
							]
						}
					},
					"response": []
				},
				{
					"name": "Post Business Event",
					"request": {
						"auth": {
							"type": "bearer",
							"bearer": [
								{
									"key": "token",
									"value": "{{token}}",
									"type": "string"
								}
							]
						},
						"method": "POST",
						"header": [],
						"body": {
							"mode": "raw",
							"raw": "{\r\n    \"Name\" : \"Employee Onboarded\",\r\n    \"Description\" : \"New Employee has be onboarded\",\r\n    \"EntityType\" : \"Employee\",\r\n    \"PayloadSchema\" : \"Name : Bob Smith\"\r\n}\r\n",
							"options": {
								"raw": {
									"language": "json"
								}
							}
						},
						"url": {
							"raw": "{{ServerURL}}/Organizations/8b17fd7e-88f9-4530-beff-a183a44956fa/IntegrationEvents/BusinessEvents\n",
							"host": [
								"{{ServerURL}}"
							],
							"path": [
								"Organizations",
								"8b17fd7e-88f9-4530-beff-a183a44956fa",
								"IntegrationEvents",
								"BusinessEvents\n"
							]
						}
					},
					"response": []
				},
				{
					"name": "Raise Business Event",
					"request": {
						"auth": {
							"type": "bearer",
							"bearer": [
								{
									"key": "token",
									"value": "{{token}}",
									"type": "string"
								}
							]
						},
						"method": "POST",
						"header": [],
						"body": {
							"mode": "raw",
							"raw": "{\r\n    \"EntityID\" : \"a68d0783-594f-4b44-b7dd-d0b7c3753b0b\",\r\n    \"EntityName\" : \"John Smith\"\r\n}\r\n",
							"options": {
								"raw": {
									"language": "json"
								}
							}
						},
						"url": {
							"raw": "{{ServerURL}}/Organizations/8b17fd7e-88f9-4530-beff-a183a44956fa/IntegrationEvents/BusinessEvents/RaiseEvent/d07de8de-3402-4994-9f24-1abaa0bcb03d\n",
							"host": [
								"{{ServerURL}}"
							],
							"path": [
								"Organizations",
								"8b17fd7e-88f9-4530-beff-a183a44956fa",
								"IntegrationEvents",
								"BusinessEvents",
								"RaiseEvent",
								"d07de8de-3402-4994-9f24-1abaa0bcb03d\n"
							]
						}
					},
					"response": []
				},
				{
					"name": "Update Business Event",
					"request": {
						"auth": {
							"type": "bearer",
							"bearer": [
								{
									"key": "token",
									"value": "{{token}}",
									"type": "string"
								}
							]
						},
						"method": "PUT",
						"header": [],
						"body": {
							"mode": "raw",
							"raw": "{\r\n    \"Name\" : \"Employee Onboarded\",\r\n    \"Description\" : \"New Employee has be onboarded\",\r\n    \"EntityType\" : \"Employee\",\r\n    \"PayloadSchema\" : \"Name : Bob Smith\"\r\n}\r\n",
							"options": {
								"raw": {
									"language": "json"
								}
							}
						},
						"url": {
							"raw": "{{ServerURL}}/Organizations/8b17fd7e-88f9-4530-beff-a183a44956fa/IntegrationEvents/BusinessEvents/d07de8de-3402-4994-9f24-1abaa0bcb03d",
							"host": [
								"{{ServerURL}}"
							],
							"path": [
								"Organizations",
								"8b17fd7e-88f9-4530-beff-a183a44956fa",
								"IntegrationEvents",
								"BusinessEvents",
								"d07de8de-3402-4994-9f24-1abaa0bcb03d"
							]
						}
					},
					"response": []
				},
				{
					"name": "Partially Update Business Event",
					"request": {
						"auth": {
							"type": "bearer",
							"bearer": [
								{
									"key": "token",
									"value": "{{token}}",
									"type": "string"
								}
							]
						},
						"method": "PATCH",
						"header": [],
						"body": {
							"mode": "raw",
							"raw": "[\r\n    {\r\n        \"op\":\"replace\",\r\n        \"path\":\"/Name\",\r\n        \"value\":\"NewEmployee\"\r\n    }\r\n]",
							"options": {
								"raw": {
									"language": "json"
								}
							}
						},
						"url": {
							"raw": "{{ServerURL}}/Organizations/8b17fd7e-88f9-4530-beff-a183a44956fa/IntegrationEvents/BusinessEvents/d07de8de-3402-4994-9f24-1abaa0bcb03d",
							"host": [
								"{{ServerURL}}"
							],
							"path": [
								"Organizations",
								"8b17fd7e-88f9-4530-beff-a183a44956fa",
								"IntegrationEvents",
								"BusinessEvents",
								"d07de8de-3402-4994-9f24-1abaa0bcb03d"
							]
						}
					},
					"response": []
				},
				{
					"name": "Delete Existing Business Event",
					"request": {
						"auth": {
							"type": "bearer",
							"bearer": [
								{
									"key": "token",
									"value": "{{token}}",
									"type": "string"
								}
							]
						},
						"method": "DELETE",
						"header": [],
						"url": {
							"raw": "{{ServerURL}}/Organizations/8b17fd7e-88f9-4530-beff-a183a44956faIntegrationEvents/d07de8de-3402-4994-9f24-1abaa0bcb03d",
							"host": [
								"{{ServerURL}}"
							],
							"path": [
								"Organizations",
								"8b17fd7e-88f9-4530-beff-a183a44956faIntegrationEvents",
								"d07de8de-3402-4994-9f24-1abaa0bcb03d"
							]
						}
					},
					"response": []
				}
			],
			"description": "ReadOnly API containing details about all existing integration events"
		},
		{
			"name": "Integration Event Subscriptions",
			"item": [
				{
					"name": "Get All Subscriptions ",
					"request": {
						"auth": {
							"type": "bearer",
							"bearer": [
								{
									"key": "token",
									"value": "{{token}}",
									"type": "string"
								}
							]
						},
						"method": "GET",
						"header": [],
						"url": {
							"raw": "{{ServerURL}}/organizations/ef8a6670-f522-4fcd-a55e-90aa92d1deb7/IntegrationEventSubscriptions",
							"host": [
								"{{ServerURL}}"
							],
							"path": [
								"organizations",
								"ef8a6670-f522-4fcd-a55e-90aa92d1deb7",
								"IntegrationEventSubscriptions"
							]
						},
						"description": "Provides a list of all Integration Event Subscriptions"
					},
					"response": []
				},
				{
					"name": "Get Integration Event Subscription by ID",
					"request": {
						"auth": {
							"type": "bearer",
							"bearer": [
								{
									"key": "token",
									"value": "{{token}}",
									"type": "string"
								}
							]
						},
						"method": "GET",
						"header": [],
						"url": {
							"raw": "{{ServerURL}}/organizations/ef8a6670-f522-4fcd-a55e-90aa92d1deb7/IntegrationEventSubscriptions/241fd289-76ae-499b-b9ee-d2f3d9b3db69",
							"host": [
								"{{ServerURL}}"
							],
							"path": [
								"organizations",
								"ef8a6670-f522-4fcd-a55e-90aa92d1deb7",
								"IntegrationEventSubscriptions",
								"241fd289-76ae-499b-b9ee-d2f3d9b3db69"
							]
						},
						"description": "Provides an IntegrationEventSubscription's details for a particular IntegrationEventSubscription id"
					},
					"response": []
				},
				{
					"name": "Post New IntegrationEventSubscription",
					"request": {
						"auth": {
							"type": "bearer",
							"bearer": [
								{
									"key": "token",
									"value": "{{token}}",
									"type": "string"
								}
							]
						},
						"method": "POST",
						"header": [],
						"body": {
							"mode": "raw",
							"raw": "{\r\n  \"id\": \"3fa85f64-5717-4562-b3fc-2c963f66afa6\",\r\n  \"name\": \"FirstSubscription\",\r\n  \"entityType\": \"Agent\",\r\n  \"integrationEventName\": \"Agent.UnhealthyReported\",\r\n  \"entityID\": \"\",\r\n  \"entityName\": \"\",\r\n  \"transportType\": \"HTTPS\",\r\n  \"httP_URL\": \"https://localhost:5001/api/WebhooksClient\",\r\n  \"httP_AddHeader_Key\": \"string\",\r\n  \"httP_AddHeader_Value\": \"string\",\r\n  \"httP_Max_RetryCount\": 0,\r\n  \"queuE_QueueID\": \"3fa85f64-5717-4562-b3fc-2c963f66afa6\"\r\n}",
							"options": {
								"raw": {
									"language": "json"
								}
							}
						},
						"url": {
							"raw": "{{ServerURL}}/organizations/ef8a6670-f522-4fcd-a55e-90aa92d1deb7/IntegrationEventSubscriptions/",
							"host": [
								"{{ServerURL}}"
							],
							"path": [
								"organizations",
								"ef8a6670-f522-4fcd-a55e-90aa92d1deb7",
								"IntegrationEventSubscriptions",
								""
							]
						},
						"description": "Adds a new IntegrationEvntSubscription to the existing subscriptions"
					},
					"response": []
				},
				{
					"name": "PUT Update an IntegrationEventSubscription",
					"request": {
						"auth": {
							"type": "bearer",
							"bearer": [
								{
									"key": "token",
									"value": "{{token}}",
									"type": "string"
								}
							]
						},
						"method": "PUT",
						"header": [],
						"url": {
							"raw": "{{ServerURL}}/organizations/ef8a6670-f522-4fcd-a55e-90aa92d1deb7/IntegrationEventSubscriptions/241fd289-76ae-499b-b9ee-d2f3d9b3db69",
							"host": [
								"{{ServerURL}}"
							],
							"path": [
								"organizations",
								"ef8a6670-f522-4fcd-a55e-90aa92d1deb7",
								"IntegrationEventSubscriptions",
								"241fd289-76ae-499b-b9ee-d2f3d9b3db69"
							]
						},
						"description": "Updates an IntegrationEventSubscription entity when the id of an existing subscription is given"
					},
					"response": []
				},
				{
					"name": "Delete an IntegrationEventSubscription",
					"request": {
						"auth": {
							"type": "bearer",
							"bearer": [
								{
									"key": "token",
									"value": "{{token}}",
									"type": "string"
								}
							]
						},
						"method": "DELETE",
						"header": [],
						"url": {
							"raw": "{{ServerURL}}/organizations/ef8a6670-f522-4fcd-a55e-90aa92d1deb7/IntegrationEventSubscriptions/241fd289-76ae-499b-b9ee-d2f3d9b3db69",
							"host": [
								"{{ServerURL}}"
							],
							"path": [
								"organizations",
								"ef8a6670-f522-4fcd-a55e-90aa92d1deb7",
								"IntegrationEventSubscriptions",
								"241fd289-76ae-499b-b9ee-d2f3d9b3db69"
							]
						},
						"description": "Deletes an IntegrationEventSubscription with a specified id"
					},
					"response": []
				},
				{
					"name": "Patch Update an IntegrationEventSubscription",
					"request": {
						"auth": {
							"type": "bearer",
							"bearer": [
								{
									"key": "token",
									"value": "{{token}}",
									"type": "string"
								}
							]
						},
						"method": "PATCH",
						"header": [],
						"body": {
							"mode": "raw",
							"raw": "[\r\n    {\r\n        \"op\":\"replace\",\r\n        \"path\":\"Name\",\r\n        \"value\":\"AgentsSubscription\"\r\n    }\r\n]",
							"options": {
								"raw": {
									"language": "json"
								}
							}
						},
						"url": {
							"raw": "{{ServerURL}}/organizations/ef8a6670-f522-4fcd-a55e-90aa92d1deb7/IntegrationEventSubscriptions/241fd289-76ae-499b-b9ee-d2f3d9b3db69",
							"host": [
								"{{ServerURL}}"
							],
							"path": [
								"organizations",
								"ef8a6670-f522-4fcd-a55e-90aa92d1deb7",
								"IntegrationEventSubscriptions",
								"241fd289-76ae-499b-b9ee-d2f3d9b3db69"
							]
						},
						"description": "Updates partial details of IntegrationEventSubscription"
					},
					"response": []
				}
			],
			"description": "API endpoint used to manager Event Subscriptions\r\n"
		},
		{
			"name": "Integration Event Log",
			"item": [
				{
					"name": "Get All Integration Event Logs",
					"request": {
						"auth": {
							"type": "bearer",
							"bearer": [
								{
									"key": "token",
									"value": "{{token}}",
									"type": "string"
								}
							]
						},
						"method": "GET",
						"header": [],
						"url": {
							"raw": "{{ServerURL}}/organizations/ef8a6670-f522-4fcd-a55e-90aa92d1deb7/IntegrationEventLogs",
							"host": [
								"{{ServerURL}}"
							],
							"path": [
								"organizations",
								"ef8a6670-f522-4fcd-a55e-90aa92d1deb7",
								"IntegrationEventLogs"
							]
						},
						"description": "Provides a list of all IntegrationEventLogs"
					},
					"response": []
				},
				{
					"name": "Get Integration Event Log by ID",
					"request": {
						"method": "GET",
						"header": [],
						"url": {
							"raw": "{{ServerURL}}/organizations/ef8a6670-f522-4fcd-a55e-90aa92d1deb7/IntegrationEventLogs/106da986-9e32-4ad4-897e-8b97a5dfe760",
							"host": [
								"{{ServerURL}}"
							],
							"path": [
								"organizations",
								"ef8a6670-f522-4fcd-a55e-90aa92d1deb7",
								"IntegrationEventLogs",
								"106da986-9e32-4ad4-897e-8b97a5dfe760"
							]
						},
						"description": "Gets an integration event log for the specified log ID"
					},
					"response": []
				},
				{
					"name": "Export Payload For the Specified Integration Event",
					"request": {
						"auth": {
							"type": "bearer",
							"bearer": [
								{
									"key": "token",
									"value": "{{token}}",
									"type": "string"
								}
							]
						},
						"method": "GET",
						"header": [],
						"url": {
							"raw": "{{ServerURL}}/IntegrationEventLogs/ExportPayload/106da986-9e32-4ad4-897e-8b97a5dfe760",
							"host": [
								"{{ServerURL}}"
							],
							"path": [
								"IntegrationEventLogs",
								"ExportPayload",
								"106da986-9e32-4ad4-897e-8b97a5dfe760"
							]
						},
						"description": "Export the payload corresponding to the specified attempt"
					},
					"response": []
				},
				{
					"name": "Lookup for all integrationEvent names",
					"request": {
						"auth": {
							"type": "bearer",
							"bearer": [
								{
									"key": "token",
									"value": "{{token}}",
									"type": "string"
								}
							]
						},
						"method": "GET",
						"header": [],
						"url": {
							"raw": "{{ServerURL}}/organizations/ef8a6670-f522-4fcd-a55e-90aa92d1deb7/IntegrationEventLogs/IntegrationEventLogsLookup",
							"host": [
								"{{ServerURL}}"
							],
							"path": [
								"organizations",
								"ef8a6670-f522-4fcd-a55e-90aa92d1deb7",
								"IntegrationEventLogs",
								"IntegrationEventLogsLookup"
							]
						},
						"description": "Provides a list of all integration event logs by name\r\n"
					},
					"response": []
				}
			],
			"description": "Keeps a log of all integration events that have occured"
		},
		{
			"name": "Integration Event Subscription Attempt",
			"item": [
				{
					"name": "Get All Integregration Event Subscription Atemmpts",
					"request": {
						"auth": {
							"type": "bearer",
							"bearer": [
								{
									"key": "token",
									"value": "{{token}}",
									"type": "string"
								}
							]
						},
						"method": "GET",
						"header": [],
						"url": {
							"raw": "{{ServerURL}}/organizations/ef8a6670-f522-4fcd-a55e-90aa92d1deb7/IntegrationEventSubscriptionAttempts",
							"host": [
								"{{ServerURL}}"
							],
							"path": [
								"organizations",
								"ef8a6670-f522-4fcd-a55e-90aa92d1deb7",
								"IntegrationEventSubscriptionAttempts"
							]
						}
					},
					"response": []
				},
				{
					"name": "Get SubscriptionAttempt by id",
					"request": {
						"auth": {
							"type": "bearer",
							"bearer": [
								{
									"key": "token",
									"value": "{{token}}",
									"type": "string"
								}
							]
						},
						"method": "GET",
						"header": [],
						"url": {
							"raw": "{{ServerURL}}/organizations/ef8a6670-f522-4fcd-a55e-90aa92d1deb7/IntegrationEventSubscriptionAttempts/2c3bb851-087b-4c05-9e4f-002c02350dad",
							"host": [
								"{{ServerURL}}"
							],
							"path": [
								"organizations",
								"ef8a6670-f522-4fcd-a55e-90aa92d1deb7",
								"IntegrationEventSubscriptionAttempts",
								"2c3bb851-087b-4c05-9e4f-002c02350dad"
							]
						},
						"description": "Gets details of the IntegrationEventSubscriptionAttempt corresponding to the provided Guid"
					},
					"response": []
				}
			],
			"description": "Keeps a log of each attempt to send a webhook to an event subscription"
		}
	]
}